abcLR/__init__.py
abcLR/main.py
abcLR-1.0.1.dist-info/LICENSE.txt
abcLR-1.0.1.dist-info/METADATA
abcLR-1.0.1.dist-info/WHEEL
abcLR-1.0.1.dist-info/top_level.txt
abcLR-1.0.1.dist-info/RECORD
