Metadata-Version: 2.1
Name: abcLR
Version: 1.0.1
Summary: ABC-LR is a classification method that combines the Artificial Bee Colony algorithm with a logistic regression classification model.
Home-page: https://github.com/kagandedeturk/ABC-LR
Author: Bilge Kagan Dedeturk
Author-email: kagandedeturk@gmail.com; bilgededeturk@erciyes.edu.tr
Classifier: Programming Language :: Python :: 3.7
Classifier: Programming Language :: Python :: 3.10
Classifier: License :: OSI Approved :: BSD License
Classifier: Operating System :: OS Independent
License-File: LICENSE.txt
